anova/AnovaCooker.py
anova/__init__.py
pyanova_api-0.0.1.dist-info/LICENSE
pyanova_api-0.0.1.dist-info/METADATA
pyanova_api-0.0.1.dist-info/WHEEL
pyanova_api-0.0.1.dist-info/top_level.txt
pyanova_api-0.0.1.dist-info/RECORD
