Metadata-Version: 2.1
Name: pyanova-api
Version: 0.0.1
Summary: A Python 3 library for programmatically accessing Anova WiFi-enabled sous vide cookers through the Anova API.
Home-page: https://github.com/ammarzuberi/pyanova-api
Author: Ammar Zuberi
Author-email: az@0f.tf
License: UNKNOWN
Platform: UNKNOWN
Requires-Python: >=3.6
Requires-Dist: requests
